azure/communication/email/__init__.py
azure/communication/email/_api_versions.py
azure/communication/email/_email_client.py
azure/communication/email/_version.py
azure/communication/email/py.typed
azure/communication/email/_generated/__init__.py
azure/communication/email/_generated/_client.py
azure/communication/email/_generated/_configuration.py
azure/communication/email/_generated/_patch.py
azure/communication/email/_generated/_serialization.py
azure/communication/email/_generated/_vendor.py
azure/communication/email/_generated/_version.py
azure/communication/email/_generated/aio/__init__.py
azure/communication/email/_generated/aio/_client.py
azure/communication/email/_generated/aio/_configuration.py
azure/communication/email/_generated/aio/_patch.py
azure/communication/email/_generated/aio/operations/__init__.py
azure/communication/email/_generated/aio/operations/_operations.py
azure/communication/email/_generated/aio/operations/_patch.py
azure/communication/email/_generated/operations/__init__.py
azure/communication/email/_generated/operations/_operations.py
azure/communication/email/_generated/operations/_patch.py
azure/communication/email/_shared/__init__.py
azure/communication/email/_shared/models.py
azure/communication/email/_shared/policy.py
azure/communication/email/_shared/user_credential.py
azure/communication/email/_shared/user_credential_async.py
azure/communication/email/_shared/utils.py
azure/communication/email/_shared/utils_async.py
azure/communication/email/aio/__init__.py
azure/communication/email/aio/_email_client_async.py
azure_communication_email-1.0.0.dist-info/LICENSE
azure_communication_email-1.0.0.dist-info/METADATA
azure_communication_email-1.0.0.dist-info/WHEEL
azure_communication_email-1.0.0.dist-info/top_level.txt
azure_communication_email-1.0.0.dist-info/RECORD
